github_ssh_auth/__init__.py
github_ssh_auth/_static_version.py
github_ssh_auth/_version.py
github_ssh_auth/cli.py
github_ssh_auth-1.0.2.dist-info/LICENSE
github_ssh_auth-1.0.2.dist-info/METADATA
github_ssh_auth-1.0.2.dist-info/WHEEL
github_ssh_auth-1.0.2.dist-info/entry_points.txt
github_ssh_auth-1.0.2.dist-info/top_level.txt
github_ssh_auth-1.0.2.dist-info/RECORD
